gopiscator/__init__.py
gopiscator/__main__.py
gopiscator/cli.py
gopiscator/data_processing.py
gopiscator/go_processing.py
gopiscator/utils.py
gopiscator-0.1.5.dist-info/LICENSE
gopiscator-0.1.5.dist-info/METADATA
gopiscator-0.1.5.dist-info/WHEEL
gopiscator-0.1.5.dist-info/entry_points.txt
gopiscator-0.1.5.dist-info/top_level.txt
gopiscator-0.1.5.dist-info/RECORD
