Metadata-Version: 2.1
Name: gopiscator
Version: 0.1.5
Summary: CLI tool for performing gene set enrichment analysis using the GO database.
Author-email: Dmitry Bespiatykh <d.bespiatykh@gmail.com>
License: MIT License
Project-URL: Homepage, https://github.com/dbespiatykh/gopiscator
Project-URL: Documentation, https://github.com/dbespiatykh/gopiscator
Project-URL: Issues, https://github.com/dbespiatykh/gopiscator/issues
Project-URL: Repository, https://github.com/dbespiatykh/gopiscator
Keywords: go,enrichment,gene,ontology,fisher
Classifier: Programming Language :: Python
Classifier: Programming Language :: Python :: 3
Classifier: Programming Language :: Python :: 3.10
Classifier: Programming Language :: Python :: 3.11
Classifier: Programming Language :: Python :: 3.12
Classifier: Environment :: Console
Classifier: Intended Audience :: Science/Research
Classifier: License :: OSI Approved :: MIT License
Classifier: Topic :: Scientific/Engineering :: Bio-Informatics
Requires-Python: >=3.10
License-File: LICENSE
Requires-Dist: click
Requires-Dist: pandas
Requires-Dist: numpy
Requires-Dist: statsmodels
Requires-Dist: goatools
Requires-Dist: tabulate
Requires-Dist: tqdm
